{"data": [{"values": [{"global_average": 86.645359999999997, "value": 58.2, "year": 2014}], "name": "Spot", "id": "spot_electricity"}, {"values": [{"global_average": 135.83349875000002, "value": 87.0, "year": 2014}], "name": "Retail Avg", "id": "retail_electricity"}, {"values": [{"global_average": 119.85706363636368, "value": 74.22, "year": 2014}], "name": "Residential", "id": "residential_electricity"}, {"values": [{"global_average": 162.95029199999999, "value": 121.55, "year": 2014}], "name": "Commercial", "id": "commercial_electricity"}, {"values": [{"global_average": 123.83284799999998, "value": 94.37, "year": 2014}], "name": "Industrial", "id": "industrial_electricity"}], "meta": {"label-y": "", "label-x": "USD/MWh", "title": "Price attractiveness"}, "iso": "in-ka", "name": "in-ka"}