{"data": [{"values": [{"value": "-", "year": 2006}, {"value": "36.44", "year": 2007}, {"value": "36.44", "year": 2008}, {"value": "36.44", "year": 2009}, {"value": "73.69", "year": 2010}, {"value": "126.3", "year": 2011}, {"value": "232.3", "year": 2012}, {"value": "232.3", "year": 2013}], "name": "DO", "id": "country"}, {"values": [{"value": "-", "year": 2006}, {"value": "36.44", "year": 2007}, {"value": "36.44", "year": 2008}, {"value": "36.44", "year": 2009}, {"value": "73.69", "year": 2010}, {"value": "126.3", "year": 2011}, {"value": "232.3", "year": 2012}, {"value": "232.3", "year": 2013}], "name": "Regional average", "id": "regional"}, {"values": [{"value": "-", "year": 2006}, {"value": "36.44", "year": 2007}, {"value": "36.44", "year": 2008}, {"value": "36.44", "year": 2009}, {"value": "73.69", "year": 2010}, {"value": "126.3", "year": 2011}, {"value": "232.3", "year": 2012}, {"value": "232.3", "year": 2013}], "name": "Global average", "id": "global"}], "meta": {"label-y": "USDm", "label-x": "year", "title": "Clean energy investments"}, "iso": "do", "name": "do"}